{"v":"5.7.11","fr":30,"ip":0,"op":37,"w":500,"h":500,"nm":"LowEth","ddd":0,"assets":[],"layers":[{"ddd":0,"ind":1,"ty":4,"nm":"Layer 1 Outlines","sr":1,"ks":{"o":{"a":0,"k":100,"ix":11},"r":{"a":1,"k":[{"i":{"x":[0.81],"y":[0.998]},"o":{"x":[0.233],"y":[0.071]},"t":6,"s":[0]},{"i":{"x":[0.833],"y":[0.999]},"o":{"x":[0.385],"y":[-0.003]},"t":11,"s":[5.908]},{"i":{"x":[0.823],"y":[1.002]},"o":{"x":[0.376],"y":[-0.001]},"t":16,"s":[-3.04]},{"i":{"x":[0.301],"y":[1]},"o":{"x":[0.248],"y":[0.008]},"t":21,"s":[4.445]},{"t":31,"s":[0]}],"ix":10},"p":{"a":0,"k":[250,234,0],"ix":2,"l":2},"a":{"a":0,"k":[552,700,0],"ix":1,"l":2},"s":{"a":0,"k":[86.91,86.91,100],"ix":6,"l":2}},"ao":0,"shapes":[{"ty":"gr","it":[{"ind":0,"ty":"sh","ix":1,"ks":{"a":0,"k":{"i":[[0,0],[0,0]],"o":[[0,0],[0,0]],"v":[[0.311,56.5],[-0.31,-56.5]],"c":false},"ix":2},"nm":"Path 1","mn":"ADBE Vector Shape - Group","hd":false},{"ty":"tm","s":{"a":0,"k":0,"ix":1},"e":{"a":0,"k":100,"ix":2},"o":{"a":0,"k":0,"ix":3},"m":1,"ix":2,"nm":"Trim Paths 1","mn":"ADBE Vector Filter - Trim","hd":false},{"ty":"fl","c":{"a":0,"k":[0,0,0,1],"ix":4},"o":{"a":0,"k":100,"ix":5},"r":1,"bm":0,"nm":"Fill 1","mn":"ADBE Vector Graphic - Fill","hd":false},{"ty":"gs","o":{"a":0,"k":100,"ix":9},"w":{"a":0,"k":14,"ix":10},"g":{"p":3,"k":{"a":0,"k":[0,0.822,0.304,0.963,0.5,0.803,0.389,0.713,1,0.784,0.475,0.463],"ix":8}},"s":{"a":0,"k":[-255.64,0],"ix":4},"e":{"a":0,"k":[246.276,0],"ix":5},"t":1,"lc":2,"lj":1,"ml":4,"ml2":{"a":0,"k":4,"ix":13},"bm":0,"nm":"Gradient Stroke 1","mn":"ADBE Vector Graphic - G-Stroke","hd":false},{"ty":"tr","p":{"a":0,"k":[552.494,889.5],"ix":2},"a":{"a":0,"k":[0,0],"ix":1},"s":{"a":0,"k":[100,100],"ix":3},"r":{"a":0,"k":0,"ix":6},"o":{"a":0,"k":100,"ix":7},"sk":{"a":0,"k":0,"ix":4},"sa":{"a":0,"k":0,"ix":5},"nm":"Transform"}],"nm":"Group 1","np":4,"cix":2,"bm":0,"ix":1,"mn":"ADBE Vector Group","hd":false},{"ty":"gr","it":[{"ind":0,"ty":"sh","ix":1,"ks":{"a":0,"k":{"i":[[0,0],[0,0]],"o":[[0,0],[0,0]],"v":[[0.311,159.583],[-0.31,-159.583]],"c":false},"ix":2},"nm":"Path 1","mn":"ADBE Vector Shape - Group","hd":false},{"ty":"fl","c":{"a":0,"k":[0,0,0,1],"ix":4},"o":{"a":0,"k":100,"ix":5},"r":1,"bm":0,"nm":"Fill 1","mn":"ADBE Vector Graphic - Fill","hd":false},{"ty":"gs","o":{"a":0,"k":100,"ix":9},"w":{"a":0,"k":14,"ix":10},"g":{"p":3,"k":{"a":0,"k":[0,0.822,0.304,0.963,0.5,0.803,0.389,0.713,1,0.784,0.475,0.463],"ix":8}},"s":{"a":0,"k":[-255.64,0],"ix":4},"e":{"a":0,"k":[246.276,0],"ix":5},"t":1,"lc":2,"lj":1,"ml":4,"ml2":{"a":0,"k":4,"ix":13},"bm":0,"nm":"Gradient Stroke 1","mn":"ADBE Vector Graphic - G-Stroke","hd":false},{"ty":"tm","s":{"a":0,"k":0,"ix":1},"e":{"a":0,"k":100,"ix":2},"o":{"a":0,"k":0,"ix":3},"m":1,"ix":4,"nm":"Trim Paths 1","mn":"ADBE Vector Filter - Trim","hd":false},{"ty":"tr","p":{"a":0,"k":[552.494,646.583],"ix":2},"a":{"a":0,"k":[0,0],"ix":1},"s":{"a":0,"k":[100,100],"ix":3},"r":{"a":0,"k":0,"ix":6},"o":{"a":0,"k":100,"ix":7},"sk":{"a":0,"k":0,"ix":4},"sa":{"a":0,"k":0,"ix":5},"nm":"Transform"}],"nm":"Group 2","np":4,"cix":2,"bm":0,"ix":2,"mn":"ADBE Vector Group","hd":false},{"ty":"gr","it":[{"ind":0,"ty":"sh","ix":1,"ks":{"a":0,"k":{"i":[[0,0],[0,0],[0,0]],"o":[[0,0],[0,0],[0,0]],"v":[[-135.619,32.938],[-0.179,-32.938],[135.619,26.979]],"c":false},"ix":2},"nm":"Path 1","mn":"ADBE Vector Shape - Group","hd":false},{"ty":"gs","o":{"a":0,"k":100,"ix":9},"w":{"a":0,"k":14,"ix":10},"g":{"p":3,"k":{"a":0,"k":[0,0.822,0.304,0.963,0.5,0.803,0.389,0.713,1,0.784,0.475,0.463],"ix":8}},"s":{"a":0,"k":[-255.64,0],"ix":4},"e":{"a":0,"k":[246.276,0],"ix":5},"t":1,"lc":2,"lj":1,"ml":4,"ml2":{"a":0,"k":4,"ix":13},"bm":0,"nm":"Gradient Stroke 1","mn":"ADBE Vector Graphic - G-Stroke","hd":false},{"ty":"tm","s":{"a":0,"k":0,"ix":1},"e":{"a":0,"k":100,"ix":2},"o":{"a":0,"k":0,"ix":3},"m":1,"ix":3,"nm":"Trim Paths 1","mn":"ADBE Vector Filter - Trim","hd":false},{"ty":"tr","p":{"a":0,"k":[552.604,689.438],"ix":2},"a":{"a":0,"k":[0,0],"ix":1},"s":{"a":0,"k":[100,100],"ix":3},"r":{"a":0,"k":0,"ix":6},"o":{"a":0,"k":100,"ix":7},"sk":{"a":0,"k":0,"ix":4},"sa":{"a":0,"k":0,"ix":5},"nm":"Transform"}],"nm":"Group 3","np":3,"cix":2,"bm":0,"ix":3,"mn":"ADBE Vector Group","hd":false},{"ty":"gr","it":[{"ind":0,"ty":"sh","ix":1,"ks":{"a":0,"k":{"i":[[45.893,-65.527],[45.358,64.765],[-0.164,0.233],[-3.701,-2.304],[-40.354,-25.256],[-2.87,1.795],[-43.398,26.976],[-1.426,-0.176]],"o":[[-45.964,-65.631],[0.164,-0.234],[3.729,2.26],[40.419,25.15],[2.796,1.75],[43.325,-27.092],[0.695,-0.432],[-45.409,64.838]],"v":[[-0.015,97.93],[-136.695,-97.231],[-136.204,-97.93],[-125.022,-91.142],[-3.819,-15.602],[3.729,-15.586],[133.871,-96.597],[136.695,-97.273]],"c":true},"ix":2},"nm":"Path 1","mn":"ADBE Vector Shape - Group","hd":false},{"ty":"gs","o":{"a":0,"k":100,"ix":9},"w":{"a":0,"k":14,"ix":10},"g":{"p":3,"k":{"a":0,"k":[0,0.822,0.304,0.963,0.5,0.803,0.389,0.713,1,0.784,0.475,0.463],"ix":8}},"s":{"a":0,"k":[-255.64,0],"ix":4},"e":{"a":0,"k":[246.276,0],"ix":5},"t":1,"lc":2,"lj":2,"bm":0,"nm":"Gradient Stroke 1","mn":"ADBE Vector Graphic - G-Stroke","hd":false},{"ty":"tm","s":{"a":0,"k":0,"ix":1},"e":{"a":0,"k":100,"ix":2},"o":{"a":0,"k":0,"ix":3},"m":1,"ix":3,"nm":"Trim Paths 1","mn":"ADBE Vector Filter - Trim","hd":false},{"ty":"tr","p":{"a":0,"k":[552.804,847.94],"ix":2},"a":{"a":0,"k":[0,0],"ix":1},"s":{"a":0,"k":[100,100],"ix":3},"r":{"a":0,"k":0,"ix":6},"o":{"a":0,"k":100,"ix":7},"sk":{"a":0,"k":0,"ix":4},"sa":{"a":0,"k":0,"ix":5},"nm":"Transform"}],"nm":"Group 4","np":3,"cix":2,"bm":0,"ix":4,"mn":"ADBE Vector Group","hd":false},{"ty":"gr","it":[{"ind":0,"ty":"sh","ix":1,"ks":{"a":0,"k":{"i":[[1.055,0.759],[-46.163,78.338],[-0.786,-1.333],[-44.319,-74.946],[3.45,-2.139],[43.22,-26.977],[2.583,1.616],[44.225,27.57]],"o":[[45.907,-77.904],[1.202,1.782],[44.194,75.02],[2.387,4.037],[-43.302,26.846],[-2.313,1.444],[-44.175,-27.65],[-0.556,-0.347]],"v":[[-137.874,73.957],[-0.096,-159.855],[2.829,-155.496],[135.487,69.52],[133.354,77.208],[3.599,157.985],[-3.109,158.239],[-135.75,75.479]],"c":true},"ix":2},"nm":"Path 1","mn":"ADBE Vector Shape - Group","hd":false},{"ty":"gs","o":{"a":0,"k":100,"ix":9},"w":{"a":0,"k":14,"ix":10},"g":{"p":3,"k":{"a":0,"k":[0,0.822,0.304,0.963,0.5,0.803,0.389,0.713,1,0.784,0.475,0.463],"ix":8}},"s":{"a":0,"k":[-255.64,0],"ix":4},"e":{"a":0,"k":[246.276,0],"ix":5},"t":1,"lc":2,"lj":2,"bm":0,"nm":"Gradient Stroke 1","mn":"ADBE Vector Graphic - G-Stroke","hd":false},{"ty":"tm","s":{"a":0,"k":0,"ix":1},"e":{"a":0,"k":100,"ix":2},"o":{"a":0,"k":0,"ix":3},"m":1,"ix":3,"nm":"Trim Paths 1","mn":"ADBE Vector Filter - Trim","hd":false},{"ty":"tr","p":{"a":0,"k":[552.735,646.897],"ix":2},"a":{"a":0,"k":[0,0],"ix":1},"s":{"a":0,"k":[100,100],"ix":3},"r":{"a":0,"k":0,"ix":6},"o":{"a":0,"k":100,"ix":7},"sk":{"a":0,"k":0,"ix":4},"sa":{"a":0,"k":0,"ix":5},"nm":"Transform"}],"nm":"Group 5","np":3,"cix":2,"bm":0,"ix":5,"mn":"ADBE Vector Group","hd":false},{"ty":"gr","it":[{"ty":"gs","o":{"a":0,"k":100,"ix":9},"w":{"a":0,"k":14,"ix":10},"g":{"p":3,"k":{"a":0,"k":[0,0.822,0.304,0.963,0.5,0.803,0.389,0.713,1,0.784,0.475,0.463],"ix":8}},"s":{"a":0,"k":[-255.64,0],"ix":4},"e":{"a":0,"k":[246.276,0],"ix":5},"t":1,"lc":2,"lj":1,"ml":4,"ml2":{"a":0,"k":4,"ix":13},"bm":0,"nm":"Gradient Stroke 1","mn":"ADBE Vector Graphic - G-Stroke","hd":false},{"ty":"tm","s":{"a":0,"k":0,"ix":1},"e":{"a":0,"k":100,"ix":2},"o":{"a":0,"k":0,"ix":3},"m":1,"ix":2,"nm":"Trim Paths 1","mn":"ADBE Vector Filter - Trim","hd":false},{"ty":"tr","p":{"a":0,"k":[0,0],"ix":2},"a":{"a":0,"k":[0,0],"ix":1},"s":{"a":0,"k":[100,100],"ix":3},"r":{"a":0,"k":0,"ix":6},"o":{"a":0,"k":100,"ix":7},"sk":{"a":0,"k":0,"ix":4},"sa":{"a":0,"k":0,"ix":5},"nm":"Transform"}],"nm":"Group 6","np":2,"cix":2,"bm":0,"ix":6,"mn":"ADBE Vector Group","hd":false}],"ip":0,"op":359.10359103591,"st":0,"bm":0}],"markers":[]}